enpass2onepassword/.editorconfig
enpass2onepassword/__init__.py
enpass2onepassword/__main__.py
enpass2onepassword/migration.py
enpass2onepassword-0.3.1.dist-info/METADATA
enpass2onepassword-0.3.1.dist-info/WHEEL
enpass2onepassword-0.3.1.dist-info/entry_points.txt
enpass2onepassword-0.3.1.dist-info/licenses/LICENSE
enpass2onepassword-0.3.1.dist-info/RECORD
