Metadata-Version: 2.4
Name: enpass2onepassword
Version: 0.3.1
Summary: Tool to migrate from Enpass to 1Password
Project-URL: Repository, https://github.com/cimnine/enpass2onepassword
Author-email: Christian Mäder <mail@cimnine.ch>
License-Expression: GPL-3.0-or-later
License-File: LICENSE
Keywords: 1password,enpass
Classifier: Development Status :: 4 - Beta
Classifier: Environment :: Console
Classifier: Intended Audience :: End Users/Desktop
Classifier: Intended Audience :: System Administrators
Classifier: License :: OSI Approved :: GNU General Public License v3 or later (GPLv3+)
Classifier: Natural Language :: English
Classifier: Operating System :: OS Independent
Classifier: Programming Language :: Python :: 3
Classifier: Topic :: Desktop Environment
Classifier: Topic :: Office/Business
Classifier: Topic :: Utilities
Requires-Python: ~=3.10
Requires-Dist: aiostream<0.7,>=0.6.4
Requires-Dist: click<9,>=8.1.8
Requires-Dist: onepassword-sdk<0.2,>=0.1.5
Requires-Dist: pyrate-limiter<4,>=3.7.0
Requires-Dist: wakepy<0.11,>=0.10.1
